{
  "categories":[
    {
      "id":3,
      "name":"phone_case",
      "displayName":"phone_case",
      "icon":"http://s3.amazonaws.com/inksy-dev/product_types/icons/000/000/003/original/category_phone_case.png?1432595468",
      "materials":{
        "basic":{
          "suggested_price":30.0,
          "base_price":15.0,
          "colors":[
            {
              "id":185,
              "name":"#FFFFFF"
            },
            {
              "id":186,
              "name":"#000000"
            },
            {
              "id":187,
              "name":"#330066"
            },
            {
              "id":188,
              "name":"#020D35"
            }
          ]
        }
      },
      "products":[
        {
          "type":"phone_case",
          "icon":"http://s3.amazonaws.com/inksy-dev/product_materials/icons/000/000/047/original/n3.png?1433824923",
          "variant_name":"Note 3",
          "material_id":47,
          "pricing":{
            "base":15.0,
            "suggested_sale":30.0
          },
          "sides":{
            "front":{
              "name":"front",
              "images":{
                "shape":"http://s3.amazonaws.com/inksy-dev/product_sides/shapes/000/000/041/original/note_s3_shape.png?1432595768",
                "texture":"http://s3.amazonaws.com/inksy-dev/product_sides/textures/000/000/041/original/note_s3_texture.png?1432595768"
              },
              "area":{
                "width":87,
                "height":159,
                "offsetX":-175,
                "offsetY":-100
              },
              "printArea":{
                "unit":"mm",
                "width":93.63,
                "height":170.67
              }
            }
          }
        }
      ]
    }
  ]
}